Metadata-Version: 2.1
Name: tf2-gnn
Version: 2.14.0
Summary: TensorFlow 2.0 implementation of Graph Neural Networks.
Home-page: https://github.com/microsoft/tf2-gnn/
Author: Marc Brockschmidt
Author-email: mabrocks@microsoft.com
License: MIT
Classifier: Programming Language :: Python :: 3
Classifier: License :: OSI Approved :: MIT License
Classifier: Operating System :: OS Independent
Requires-Python: >=3.6
License-File: LICENSE
Requires-Dist: numpy
Requires-Dist: tensorflow >=2.0.0
Requires-Dist: dpu-utils >=0.2.7
Requires-Dist: h5py
Requires-Dist: packaging
